test_saurabh0402/maths_saurabh0402/__init__.py
test_saurabh0402/maths_saurabh0402/sum.py
test_saurabh0402/maths_saurabh0402.egg-info/PKG-INFO
test_saurabh0402/maths_saurabh0402.egg-info/SOURCES.txt
test_saurabh0402/maths_saurabh0402.egg-info/dependency_links.txt
test_saurabh0402/maths_saurabh0402.egg-info/top_level.txt
test_saurabh0402/test_saurabh0402.egg-info/PKG-INFO
test_saurabh0402/test_saurabh0402.egg-info/SOURCES.txt
test_saurabh0402/test_saurabh0402.egg-info/dependency_links.txt
test_saurabh0402/test_saurabh0402.egg-info/top_level.txt
test_saurabh0402-0.0.7.dist-info/LICENSE
test_saurabh0402-0.0.7.dist-info/METADATA
test_saurabh0402-0.0.7.dist-info/WHEEL
test_saurabh0402-0.0.7.dist-info/RECORD
