Metadata-Version: 2.1
Name: test-saurabh0402
Version: 0.0.7
Summary: A small example package
Home-page: https://github.com/saurabh0402/padhai
Author: Saurabh
Author-email: saurabh.kumar@peak.ai
Requires-Python: >=3.8.1,<3.12
Classifier: Development Status :: 5 - Production/Stable
Classifier: Intended Audience :: Developers
Classifier: License :: OSI Approved :: Apache Software License
Classifier: Natural Language :: English
Classifier: Operating System :: OS Independent
Classifier: Programming Language :: Python :: 3
Classifier: Programming Language :: Python :: 3.9
Classifier: Programming Language :: Python :: 3.10
Classifier: Programming Language :: Python :: 3.11
Classifier: Programming Language :: Python :: 3.8
Classifier: Topic :: Software Development :: Libraries :: Application Frameworks
Classifier: Typing :: Typed
Project-URL: Documentation, https://github.com/saurabh0402/padhai
